[1,["13d24d423@6c48a"],["_textureSource"],["cc.SpriteFrame"],0,[[[{"name":"ui_sm","rect":{"x":939,"y":949,"width":66,"height":66},"offset":{"x":0,"y":0},"originalSize":{"width":66,"height":66},"rotated":false,"capInsets":[0,0,0,0],"packable":true,"pixelsToUnit":100,"pivot":{"x":0.5,"y":0.5},"meshType":0}],[0],0,[0],[0],[0]],[[{"name":"selectbtnbg","rect":{"x":939,"y":689,"width":168,"height":74},"offset":{"x":0,"y":0},"originalSize":{"width":168,"height":74},"rotated":true,"capInsets":[0,0,0,0],"packable":true,"pixelsToUnit":100,"pivot":{"x":0.5,"y":0.5},"meshType":0}],[0],0,[0],[0],[0]],[[{"name":"Attack","rect":{"x":376,"y":505,"width":288,"height":96},"offset":{"x":0,"y":0},"originalSize":{"width":288,"height":96},"rotated":false,"capInsets":[0,0,0,0],"packable":true,"pixelsToUnit":100,"pivot":{"x":0.5,"y":0.5},"meshType":0}],[0],0,[0],[0],[0]],[[{"name":"selectbg2","rect":{"x":786,"y":689,"width":307,"height":147},"offset":{"x":0,"y":0},"originalSize":{"width":307,"height":147},"rotated":true,"capInsets":[0,0,0,0],"packable":true,"pixelsToUnit":100,"pivot":{"x":0.5,"y":0.5},"meshType":0}],[0],0,[0],[0],[0]],[[{"name":"jia","rect":{"x":145,"y":641,"width":61,"height":61},"offset":{"x":0,"y":0},"originalSize":{"width":61,"height":61},"rotated":false,"capInsets":[0,0,0,0],"packable":true,"pixelsToUnit":100,"pivot":{"x":0.5,"y":0.5},"meshType":0}],[0],0,[0],[0],[0]],[[{"name":"itembg","rect":{"x":75,"y":641,"width":64,"height":64},"offset":{"x":0,"y":0},"originalSize":{"width":64,"height":64},"rotated":false,"capInsets":[0,0,0,0],"packable":true,"pixelsToUnit":100,"pivot":{"x":0.5,"y":0.5},"meshType":0}],[0],0,[0],[0],[0]],[[{"name":"ui_xt","rect":{"x":976,"y":3,"width":612,"height":8},"offset":{"x":0,"y":0},"originalSize":{"width":612,"height":8},"rotated":true,"capInsets":[0,0,0,0],"packable":true,"pixelsToUnit":100,"pivot":{"x":0.5,"y":0.5},"meshType":0}],[0],0,[0],[0],[0]],[[{"name":"propicon6","rect":{"x":976,"y":621,"width":43,"height":51},"offset":{"x":0,"y":0},"originalSize":{"width":43,"height":51},"rotated":false,"capInsets":[0,0,0,0],"packable":true,"pixelsToUnit":100,"pivot":{"x":0.5,"y":0.5},"meshType":0}],[0],0,[0],[0],[0]],[[{"name":"ui_zbs","rect":{"x":672,"y":3,"width":720,"height":108},"offset":{"x":0,"y":0},"originalSize":{"width":720,"height":108},"rotated":true,"capInsets":[0,0,0,0],"packable":true,"pixelsToUnit":100,"pivot":{"x":0.5,"y":0.5},"meshType":0}],[0],0,[0],[0],[0]],[[{"name":"lifebg","rect":{"x":740,"y":729,"width":160,"height":40},"offset":{"x":0,"y":1},"originalSize":{"width":160,"height":42},"rotated":true,"capInsets":[92,0,21,0],"packable":true,"pixelsToUnit":100,"pivot":{"x":0.5,"y":0.5},"meshType":0}],[0],0,[0],[0],[0]],[[{"name":"ui_jsd","rect":{"x":3,"y":505,"width":367,"height":130},"offset":{"x":0,"y":0},"originalSize":{"width":367,"height":130},"rotated":false,"capInsets":[0,0,0,0],"packable":true,"pixelsToUnit":100,"pivot":{"x":0.5,"y":0.5},"meshType":0}],[0],0,[0],[0],[0]],[[{"name":"ui_gj","rect":{"x":3,"y":641,"width":66,"height":66},"offset":{"x":0,"y":0},"originalSize":{"width":66,"height":66},"rotated":false,"capInsets":[0,0,0,0],"packable":true,"pixelsToUnit":100,"pivot":{"x":0.5,"y":0.5},"meshType":0}],[0],0,[0],[0],[0]],[[{"name":"Ascend","rect":{"x":786,"y":3,"width":680,"height":184},"offset":{"x":0,"y":0},"originalSize":{"width":680,"height":184},"rotated":true,"capInsets":[0,0,0,0],"packable":true,"pixelsToUnit":100,"pivot":{"x":0.5,"y":0.5},"meshType":0}],[0],0,[0],[0],[0]],[[{"name":"blessbg1","rect":{"x":587,"y":729,"width":286,"height":147},"offset":{"x":0,"y":0},"originalSize":{"width":286,"height":147},"rotated":true,"capInsets":[0,0,0,0],"packable":true,"pixelsToUnit":100,"pivot":{"x":0.5,"y":0.5},"meshType":0}],[0],0,[0],[0],[0]],[[{"name":"gou","rect":{"x":939,"y":863,"width":80,"height":63},"offset":{"x":0,"y":0},"originalSize":{"width":80,"height":63},"rotated":true,"capInsets":[0,0,0,0],"packable":true,"pixelsToUnit":100,"pivot":{"x":0.5,"y":0.5},"meshType":0}],[0],0,[0],[0],[0]],[[{"name":"HP","rect":{"x":518,"y":607,"width":132,"height":88},"offset":{"x":0,"y":0},"originalSize":{"width":132,"height":88},"rotated":false,"capInsets":[0,0,0,0],"packable":true,"pixelsToUnit":100,"pivot":{"x":0.5,"y":0.5},"meshType":0}],[0],0,[0],[0],[0]],[[{"name":"propicon5","rect":{"x":324,"y":641,"width":45,"height":49},"offset":{"x":0,"y":0},"originalSize":{"width":45,"height":49},"rotated":false,"capInsets":[0,0,0,0],"packable":true,"pixelsToUnit":100,"pivot":{"x":0.5,"y":0.5},"meshType":0}],[0],0,[0],[0],[0]],[[{"name":"propicon4","rect":{"x":268,"y":641,"width":50,"height":43},"offset":{"x":0,"y":0},"originalSize":{"width":50,"height":43},"rotated":false,"capInsets":[0,0,0,0],"packable":true,"pixelsToUnit":100,"pivot":{"x":0.5,"y":0.5},"meshType":0}],[0],0,[0],[0],[0]],[[{"name":"propicon1","rect":{"x":212,"y":641,"width":50,"height":46},"offset":{"x":0,"y":0},"originalSize":{"width":50,"height":46},"rotated":false,"capInsets":[0,0,0,0],"packable":true,"pixelsToUnit":100,"pivot":{"x":0.5,"y":0.5},"meshType":0}],[0],0,[0],[0],[0]],[[{"name":"tishibg","rect":{"x":3,"y":948,"width":374,"height":52},"offset":{"x":0,"y":0},"originalSize":{"width":374,"height":52},"rotated":false,"capInsets":[0,0,0,0],"packable":true,"pixelsToUnit":100,"pivot":{"x":0.5,"y":0.5},"meshType":0}],[0],0,[0],[0],[0]],[[{"name":"ui_sxd","rect":{"x":3,"y":884,"width":578,"height":58},"offset":{"x":0,"y":0},"originalSize":{"width":578,"height":58},"rotated":false,"capInsets":[0,0,0,0],"packable":true,"pixelsToUnit":100,"pivot":{"x":0.5,"y":0.5},"meshType":0}],[0],0,[0],[0],[0]],[[{"name":"tzbg","rect":{"x":3,"y":729,"width":578,"height":149},"offset":{"x":0,"y":0},"originalSize":{"width":578,"height":149},"rotated":false,"capInsets":[0,0,0,0],"packable":true,"pixelsToUnit":100,"pivot":{"x":0.5,"y":0.5},"meshType":0}],[0],0,[0],[0],[0]],[[{"name":"ui_d","rect":{"x":3,"y":3,"width":663,"height":496},"offset":{"x":0,"y":0},"originalSize":{"width":663,"height":496},"rotated":false,"capInsets":[71,6,66,97],"packable":true,"pixelsToUnit":100,"pivot":{"x":0.5,"y":0.5},"meshType":0}],[0],0,[0],[0],[0]],[[{"name":"AP","rect":{"x":376,"y":607,"width":136,"height":88},"offset":{"x":0,"y":0},"originalSize":{"width":136,"height":88},"rotated":false,"capInsets":[0,0,0,0],"packable":true,"pixelsToUnit":100,"pivot":{"x":0.5,"y":0.5},"meshType":0}],[0],0,[0],[0],[0]],[[{"name":"attckbg","rect":{"x":383,"y":948,"width":160,"height":40},"offset":{"x":0,"y":1},"originalSize":{"width":160,"height":42},"rotated":false,"capInsets":[87,3,21,0],"packable":true,"pixelsToUnit":100,"pivot":{"x":0.5,"y":0.5},"meshType":0}],[0],0,[0],[0],[0]]]]
