[1,["14757ea9e@6c48a"],["_textureSource"],["cc.SpriteFrame"],0,[[[{"name":"ui_frame_cc","rect":{"x":1352,"y":3,"width":104,"height":104},"offset":{"x":0,"y":0},"originalSize":{"width":104,"height":104},"rotated":false,"capInsets":[0,0,0,0],"packable":true,"pixelsToUnit":100,"pivot":{"x":0.5,"y":0.5},"meshType":0}],[0],0,[0],[0],[0]],[[{"name":"Levelh02-1","rect":{"x":648,"y":109,"width":164,"height":164},"offset":{"x":0,"y":0},"originalSize":{"width":164,"height":164},"rotated":false,"capInsets":[0,0,0,0],"packable":true,"pixelsToUnit":100,"pivot":{"x":0.5,"y":0.5},"meshType":0}],[0],0,[0],[0],[0]],[[{"name":"ti02","rect":{"x":107,"y":3,"width":100,"height":172},"offset":{"x":0,"y":0},"originalSize":{"width":100,"height":172},"rotated":true,"capInsets":[0,0,0,0],"packable":true,"pixelsToUnit":100,"pivot":{"x":0.5,"y":0.5},"meshType":0}],[0],0,[0],[0],[0]],[[{"name":"icon-language","rect":{"x":1656,"y":3,"width":120,"height":120},"offset":{"x":0,"y":0},"originalSize":{"width":120,"height":120},"rotated":false,"capInsets":[0,0,0,0],"packable":true,"pixelsToUnit":100,"pivot":{"x":0.5,"y":0.5},"meshType":0}],[0],0,[0],[0],[0]],[[{"name":"x03","rect":{"x":1782,"y":3,"width":148,"height":152},"offset":{"x":0,"y":0},"originalSize":{"width":148,"height":152},"rotated":true,"capInsets":[0,0,0,0],"packable":true,"pixelsToUnit":100,"pivot":{"x":0.5,"y":0.5},"meshType":0}],[0],0,[0],[0],[0]],[[{"name":"diamond","rect":{"x":1351,"y":113,"width":184,"height":184},"offset":{"x":0,"y":0},"originalSize":{"width":184,"height":184},"rotated":false,"capInsets":[0,0,0,0],"packable":true,"pixelsToUnit":100,"pivot":{"x":0.5,"y":0.5},"meshType":0}],[0],0,[0],[0],[0]],[[{"name":"enemy","rect":{"x":1541,"y":129,"width":184,"height":184},"offset":{"x":0,"y":0},"originalSize":{"width":184,"height":184},"rotated":false,"capInsets":[0,0,0,0],"packable":true,"pixelsToUnit":100,"pivot":{"x":0.5,"y":0.5},"meshType":0}],[0],0,[0],[0],[0]],[[{"name":"btn_close","rect":{"x":3,"y":3,"width":98,"height":98},"offset":{"x":0,"y":0},"originalSize":{"width":98,"height":98},"rotated":false,"capInsets":[0,0,0,0],"packable":true,"pixelsToUnit":100,"pivot":{"x":0.5,"y":0.5},"meshType":0}],[0],0,[0],[0],[0]],[[{"name":"ys_03","rect":{"x":1165,"y":112,"width":180,"height":180},"offset":{"x":0,"y":0},"originalSize":{"width":180,"height":180},"rotated":false,"capInsets":[0,0,0,0],"packable":true,"pixelsToUnit":100,"pivot":{"x":0.5,"y":0.5},"meshType":0}],[0],0,[0],[0],[0]],[[{"name":"close","rect":{"x":988,"y":111,"width":171,"height":171},"offset":{"x":0,"y":0},"originalSize":{"width":171,"height":171},"rotated":false,"capInsets":[0,0,0,0],"packable":true,"pixelsToUnit":100,"pivot":{"x":0.5,"y":0.5},"meshType":0}],[0],0,[0],[0],[0]],[[{"name":"skin4","rect":{"x":819,"y":3,"width":101,"height":185},"offset":{"x":-3.5,"y":-34},"originalSize":{"width":116,"height":263},"rotated":true,"capInsets":[0,0,0,0],"packable":true,"pixelsToUnit":100,"pivot":{"x":0.5,"y":0.5},"meshType":0}],[0],0,[0],[0],[0]],[[{"name":"xtb03","rect":{"x":763,"y":280,"width":192,"height":196},"offset":{"x":0,"y":0},"originalSize":{"width":192,"height":196},"rotated":true,"capInsets":[0,0,0,0],"packable":true,"pixelsToUnit":100,"pivot":{"x":0.5,"y":0.5},"meshType":0}],[0],0,[0],[0],[0]],[[{"name":"enemy","rect":{"x":1731,"y":157,"width":184,"height":184},"offset":{"x":0,"y":0},"originalSize":{"width":184,"height":184},"rotated":false,"capInsets":[0,0,0,0],"packable":true,"pixelsToUnit":100,"pivot":{"x":0.5,"y":0.5},"meshType":0}],[0],0,[0],[0],[0]],[[{"name":"x02","rect":{"x":3,"y":109,"width":148,"height":152},"offset":{"x":0,"y":0},"originalSize":{"width":148,"height":152},"rotated":true,"capInsets":[0,0,0,0],"packable":true,"pixelsToUnit":100,"pivot":{"x":0.5,"y":0.5},"meshType":0}],[0],0,[0],[0],[0]],[[{"name":"Levelh02","rect":{"x":818,"y":110,"width":164,"height":164},"offset":{"x":0,"y":0},"originalSize":{"width":164,"height":164},"rotated":false,"capInsets":[0,0,0,0],"packable":true,"pixelsToUnit":100,"pivot":{"x":0.5,"y":0.5},"meshType":0}],[0],0,[0],[0],[0]],[[{"name":"zy","rect":{"x":1462,"y":3,"width":104,"height":188},"offset":{"x":0,"y":0},"originalSize":{"width":104,"height":188},"rotated":true,"capInsets":[0,0,0,0],"packable":true,"pixelsToUnit":100,"pivot":{"x":0.5,"y":0.5},"meshType":0}],[0],0,[0],[0],[0]],[[{"name":"icon","rect":{"x":3,"y":263,"width":184,"height":184},"offset":{"x":0,"y":0},"originalSize":{"width":184,"height":184},"rotated":false,"capInsets":[0,0,0,0],"packable":true,"pixelsToUnit":100,"pivot":{"x":0.5,"y":0.5},"meshType":0}],[0],0,[0],[0],[0]],[[{"name":"ti01","rect":{"x":285,"y":3,"width":100,"height":172},"offset":{"x":0,"y":0},"originalSize":{"width":100,"height":172},"rotated":true,"capInsets":[0,0,0,0],"packable":true,"pixelsToUnit":100,"pivot":{"x":0.5,"y":0.5},"meshType":0}],[0],0,[0],[0],[0]],[[{"name":"Character02","rect":{"x":477,"y":109,"width":165,"height":150},"offset":{"x":0,"y":0},"originalSize":{"width":165,"height":150},"rotated":false,"capInsets":[0,0,0,0],"packable":true,"pixelsToUnit":100,"pivot":{"x":0.5,"y":0.5},"meshType":0}],[0],0,[0],[0],[0]],[[{"name":"btn-off","rect":{"x":1010,"y":3,"width":154,"height":102},"offset":{"x":0,"y":0},"originalSize":{"width":154,"height":102},"rotated":false,"capInsets":[0,0,0,0],"packable":true,"pixelsToUnit":100,"pivot":{"x":0.5,"y":0.5},"meshType":0}],[0],0,[0],[0],[0]],[[{"name":"ti01","rect":{"x":463,"y":3,"width":100,"height":172},"offset":{"x":0,"y":0},"originalSize":{"width":100,"height":172},"rotated":true,"capInsets":[0,0,0,0],"packable":true,"pixelsToUnit":100,"pivot":{"x":0.5,"y":0.5},"meshType":0}],[0],0,[0],[0],[0]],[[{"name":"ti02","rect":{"x":641,"y":3,"width":100,"height":172},"offset":{"x":0,"y":0},"originalSize":{"width":100,"height":172},"rotated":true,"capInsets":[0,0,0,0],"packable":true,"pixelsToUnit":100,"pivot":{"x":0.5,"y":0.5},"meshType":0}],[0],0,[0],[0],[0]],[[{"name":"Souls","rect":{"x":193,"y":263,"width":184,"height":184},"offset":{"x":0,"y":0},"originalSize":{"width":184,"height":184},"rotated":false,"capInsets":[0,0,0,0],"packable":true,"pixelsToUnit":100,"pivot":{"x":0.5,"y":0.5},"meshType":0}],[0],0,[0],[0],[0]],[[{"name":"xtb03","rect":{"x":965,"y":288,"width":192,"height":196},"offset":{"x":0,"y":0},"originalSize":{"width":192,"height":196},"rotated":false,"capInsets":[0,0,0,0],"packable":true,"pixelsToUnit":100,"pivot":{"x":0.5,"y":0.5},"meshType":0}],[0],0,[0],[0],[0]],[[{"name":"ap_task","rect":{"x":383,"y":265,"width":184,"height":184},"offset":{"x":0,"y":0},"originalSize":{"width":184,"height":184},"rotated":false,"capInsets":[0,0,0,0],"packable":true,"pixelsToUnit":100,"pivot":{"x":0.5,"y":0.5},"meshType":0}],[0],0,[0],[0],[0]],[[{"name":"diamond","rect":{"x":573,"y":279,"width":184,"height":184},"offset":{"x":0,"y":0},"originalSize":{"width":184,"height":184},"rotated":false,"capInsets":[0,0,0,0],"packable":true,"pixelsToUnit":100,"pivot":{"x":0.5,"y":0.5},"meshType":0}],[0],0,[0],[0],[0]],[[{"name":"x02","rect":{"x":161,"y":109,"width":148,"height":152},"offset":{"x":0,"y":0},"originalSize":{"width":148,"height":152},"rotated":true,"capInsets":[0,0,0,0],"packable":true,"pixelsToUnit":100,"pivot":{"x":0.5,"y":0.5},"meshType":0}],[0],0,[0],[0],[0]],[[{"name":"js_x01","rect":{"x":319,"y":109,"width":148,"height":152},"offset":{"x":0,"y":0},"originalSize":{"width":148,"height":152},"rotated":true,"capInsets":[0,0,0,0],"packable":true,"pixelsToUnit":100,"pivot":{"x":0.5,"y":0.5},"meshType":0}],[0],0,[0],[0],[0]],[[{"name":"award1","rect":{"x":1170,"y":3,"width":176,"height":103},"offset":{"x":0,"y":0},"originalSize":{"width":176,"height":103},"rotated":false,"capInsets":[0,0,0,0],"packable":true,"pixelsToUnit":100,"pivot":{"x":0.5,"y":0.5},"meshType":0}],[0],0,[0],[0],[0]]]]
